LICENSE
MANIFEST.in
README.rst
setup.py
upload.bat
radware_nlbaas_v2_rocky_driver/__init__.py
radware_nlbaas_v2_rocky_driver/another_lbaas_driver.py
radware_nlbaas_v2_rocky_driver/base_driver.py
radware_nlbaas_v2_rocky_driver/config.py
radware_nlbaas_v2_rocky_driver/exceptions.py
radware_nlbaas_v2_rocky_driver/monitoring.py
radware_nlbaas_v2_rocky_driver/radware_lbaas_driver.py
radware_nlbaas_v2_rocky_driver/rest_client.py
radware_nlbaas_v2_rocky_driver.egg-info/PKG-INFO
radware_nlbaas_v2_rocky_driver.egg-info/SOURCES.txt
radware_nlbaas_v2_rocky_driver.egg-info/dependency_links.txt
radware_nlbaas_v2_rocky_driver.egg-info/not-zip-safe
radware_nlbaas_v2_rocky_driver.egg-info/top_level.txt